transmitter.v
module transmitter (
    input  clk,
    input  [7:0] addr,
    input  [7:0] code,
    input  send,
    output reg ir_out
);

    wire [7:0] cmd = code; // Bypass decoder

    parameter CLK_FREQ = 125_000_000;
    parameter CARRIER_FREQ = 38_000;

    localparam CLK_DIV = CLK_FREQ / CARRIER_FREQ;
    localparam LEADING_PULSE = 1125000;
    localparam LEADING_SPACE = 562500;
    localparam BIT_PULSE = 70250;
    localparam BIT0_SPACE = 70250;
    localparam BIT1_SPACE = 210750;

    parameter IDLE = 0, START_PULSE = 1, START_SPACE = 2, DATA_PULSE = 3, DATA_SPACE = 4, STOP = 5;

    reg [2:0] state = IDLE;
    reg [31:0] shift_reg;
    reg [21:0] counter = 0; // Sufficient width
    reg [5:0] bit_count = 0; // Track 32 bits

    reg [15:0] carrier_counter = 0;
    reg carrier = 0;
    always @(posedge clk) begin
        if (carrier_counter == CLK_DIV-1) begin
            carrier_counter <= 0;
            carrier <= ~carrier;
        end else begin
            carrier_counter <= carrier_counter + 1;
        end
    end

    reg pulse_active = 0;

    always @(posedge clk) begin
        case (state)
            IDLE: begin
                ir_out <= 0;
                pulse_active <= 0;
                counter <= 0;
                bit_count <= 0;
                if (send) begin
                    shift_reg <= {addr, ~addr, cmd, ~cmd};
                    state <= START_PULSE;
                end
            end
            START_PULSE: begin
                pulse_active <= 1;
                if (counter < LEADING_PULSE) begin
                    counter <= counter + 1;
                end else begin
                    counter <= 0;
                    state <= START_SPACE;
                    pulse_active <= 0;
                end
                ir_out <= pulse_active ? carrier : 0;
            end
            START_SPACE: begin
                pulse_active <= 0;
                ir_out <= 0;
                if (counter < LEADING_SPACE) begin
                    counter <= counter + 1;
                end else begin
                    counter <= 0;
                    state <= DATA_PULSE;
                end
            end
            DATA_PULSE: begin
                pulse_active <= 1;
                if (counter < BIT_PULSE) begin
                    counter <= counter + 1;
                end else begin
                    counter <= 0;
                    state <= DATA_SPACE;
                    pulse_active <= 0;
                end
                ir_out <= pulse_active ? carrier : 0;
            end
            DATA_SPACE: begin
                pulse_active <= 0;
                ir_out <= 0;
                if ((shift_reg[31] && (counter < BIT1_SPACE)) || (!shift_reg[31] && (counter < BIT0_SPACE))) begin
                    counter <= counter + 1;
                end else begin
                    counter <= 0;
                    shift_reg <= shift_reg << 1;
                    bit_count <= bit_count + 1;
                    if (bit_count == 31) begin
                        state <= STOP;
                    end else begin
                        state <= DATA_PULSE;
                    end
                end
            end
            STOP: begin
                ir_out <= 0;
                pulse_active <= 0;
                state <= IDLE;
            end
        endcase
    end
endmodule

NEC_communication.srcs/sim_1/new/transmitter_tb.v
`timescale 1ns / 1ps

module transmitter_tb;

    // Inputs
    reg clk;
    reg [7:0] addr;
    reg [7:0] code;
    reg send;
    
    // Output
    wire ir_out;
    
    // Instantiate the Unit Under Test (UUT)
    transmitter uut (
        .clk(clk),
        .addr(addr),
        .code(code),
        .send(send),
        .ir_out(ir_out)
    );
    
    // Clock generation (125 MHz)
    initial begin
        clk = 0;
        forever #4 clk = ~clk;  // 8ns period = 125MHz
    end
    
    // Test stimulus
    initial begin
        // Initialize Inputs
        addr = 8'h00;
        code = 8'h5e;
        send = 0;
        
        // Wait 100ns for global reset
        #1000;
        
        // Send command
        send = 1;
        #200;
        send = 0;
        
        // Wait for transmission to complete (about 67.5ms)
        #70_000_000_0;
 
        $finish;
    end
    
    // Monitor the output
    initial begin
        $monitor("Time = %t ns, State = %d, IR_OUT = %b", $time, uut.state, ir_out);
    end
    
    // Save VCD file for waveform viewing
    initial begin
        $dumpfile("transmitter_tb.vcd");
        $dumpvars(0, transmitter_tb);
    end
endmodule

NEC_communication.sim/sim_1/behav/xsim/transmitter_tb.vcd
$date
   Tue Jul 22 01:29:38 2025
$end
$version
  v2020.2.2
$end
$timescale
  1ps
$end
$scope module transmitter_tb $end
$var reg 1 ! clk $end
$var reg 8 " addr [7:0] $end
$var reg 8 # code [7:0] $end
$var reg 1 $ send $end
$var wire 1 % ir_out $end
$scope module uut $end
$var wire 1 & clk $end
$var wire 8 ' addr [7:0] $end
$var wire 8 ( code [7:0] $end
$var wire 1 ) send $end
$var reg 1 * ir_out $end
$var wire 8 + cmd [7:0] $end
$var reg 3 , state [2:0] $end
$var reg 32 - shift_reg [31:0] $end
$var reg 22 . counter [21:0] $end
$var reg 6 / bit_count [5:0] $end
$var reg 16 0 carrier_counter [15:0] $end
$var reg 1 1 carrier $end
$var reg 1 2 pulse_active $end
$var parameter 32 3 CLK_FREQ [31:0] $end
$var parameter 32 4 CARRIER_FREQ [31:0] $end
$var parameter 32 5 CLK_DIV [31:0] $end
$var parameter 32 6 LEADING_PULSE [31:0] $end
$var parameter 32 7 LEADING_SPACE [31:0] $end
$var parameter 32 8 BIT_PULSE [31:0] $end
$var parameter 32 9 BIT0_SPACE [31:0] $end
$var parameter 32 : BIT1_SPACE [31:0] $end
$var parameter 32 ; IDLE [31:0] $end
$var parameter 32 < START_PULSE [31:0] $end
$var parameter 32 = START_SPACE [31:0] $end
$var parameter 32 > DATA_PULSE [31:0] $end
$var parameter 32 ? DATA_SPACE [31:0] $end
$var parameter 32 @ STOP [31:0] $end
$upscope $end
$upscope $end
$enddefinitions $end
#0
$dumpvars
0!
b0 "
b1011110 #
0$
x%
0&
b0 '
b1011110 (
0)
x*
b1011110 +
b0 ,
bx -
b0 .
b0 /
b0 0
01
02
b111011100110101100101000000 3
b1001010001110000 4
b110011011001 5
b100010010101010001000 6
b10001001010101000100 7
b10001001001101010 8
b10001001001101010 9
b110011011100111110 :
b0 ;
b1 <
b10 =
b11 >
b100 ?
b101 @
$end
#4000
1!
0%
1&
0*
b1 0
#8000
0!
0&
#12000
1!
1&
b10 0
#16000
0!
0&
#20000
1!
1&
b11 0
#24000
0!
0&
#28000
1!
1&
b100 0
#32000
0!
0&
#36000
1!
1&
b101 0
#40000
0!
0&
#44000
1!
1&
b110 0
#48000
0!
0&
#52000
1!
1&
b111 0
#56000
0!
0&
#60000
1!
1&
b1000 0
#64000
0!
0&
#68000
1!
1&
b1001 0
#72000
0!
0&
#76000
1!
1&
b1010 0
#80000
0!
0&
#84000
1!
1&
b1011 0
#88000
0!
0&
#92000
1!
1&
b1100 0
#96000
0!
0&
#100000
1!
1&
b1101 0
#104000
0!
0&
#108000
1!
1&
b1110 0
#112000
0!
0&
#116000
1!
1&
b1111 0
#120000
0!
0&
#124000
1!
1&
b10000 0
#128000
0!
0&
#132000
1!
1&
b10001 0
#136000
0!
0&
#140000
1!
1&
b10010 0
#144000
0!
0&
#148000
1!
1&
b10011 0
#152000
0!
0&
#156000
1!
1&
b10100 0
#160000
0!
0&
#164000
1!
1&
b10101 0
#168000
0!
0&
#172000
1!
1&
b10110 0
#176000
0!
0&
#180000
1!
1&
b10111 0
#184000
0!
0&
#188000
1!
1&
b11000 0
#192000
0!
0&
#196000
1!
1&
b11001 0
#200000
0!
0&
#204000
1!
1&
b11010 0
#208000
0!
0&
#212000
1!
1&
b11011 0
#216000
0!
0&
#220000
1!
1&
b11100 0
#224000
0!
0&
#228000
1!
1&
b11101 0
#232000
0!
0&
#236000
1!
1&
b11110 0
#240000
0!
0&
#244000
1!
1&
b11111 0
#248000
0!
0&
#252000
1!
1&
b100000 0
#256000
0!
0&
#260000
1!
1&
b100001 0
#264000
0!
0&
#268000
1!
1&
b100010 0
#272000
0!
0&
#276000
1!
1&
b100011 0
#280000
0!
0&
#284000
1!
1&
b100100 0
#288000
0!
0&
#292000
1!
1&
b100101 0
#296000
0!
0&
#300000
1!
1&
b100110 0
#304000
0!
0&
#308000
1!
1&
b100111 0
#312000
0!
0&
#316000
1!
1&
b101000 0
#320000
0!
0&
#324000
1!
1&
b101001 0
#328000
0!
0&
#332000
1!
1&
b101010 0
#336000
0!
0&
#340000
1!
1&
b101011 0
#344000
0!
0&
#348000
1!
1&
b101100 0
#352000
0!
0&
#356000
1!
1&
b101101 0
#360000
0!
0&
#364000
1!
1&
b101110 0
#368000
0!
0&
#372000
1!
1&
b101111 0
#376000
0!
0&
#380000
1!
1&
b110000 0
#384000
0!
0&
#388000
1!
1&
b110001 0
#392000
0!
0&
#396000
1!
1&
b110010 0
#400000
0!
0&
#404000
1!
1&
b110011 0
#408000
0!
0&
#412000
1!
1&
b110100 0
#416000
0!
0&
#420000
1!
1&
b110101 0
#424000
0!
0&
#428000
1!
1&
b110110 0
#432000
0!
0&
#436000
1!
1&
b110111 0
#440000
0!
0&
#444000
1!
1&
b111000 0
#448000
0!
0&
#452000
1!
1&
b111001 0
#456000
0!
0&
#460000
1!
1&
b111010 0
#464000
0!
0&
#468000
1!
1&
b111011 0
#472000
0!
0&
#476000
1!
1&
b111100 0
#480000
0!
0&
#484000
1!
1&
b111101 0
#488000
0!
0&
#492000
1!
1&
b111110 0
#496000
0!
0&
#500000
1!
1&
b111111 0
#504000
0!
0&
#508000
1!
1&
b1000000 0
#512000
0!
0&
#516000
1!
1&
b1000001 0
#520000
0!
0&
#524000
1!
1&
b1000010 0
#528000
0!
0&
#532000
1!
1&
b1000011 0
#536000
0!
0&
#540000
1!
1&
b1000100 0
#544000
0!
0&
#548000
1!
1&
b1000101 0
#552000
0!
0&
#556000
1!
1&
b1000110 0
#560000
0!
0&
#564000
1!
1&
b1000111 0
#568000
0!
0&
#572000
1!
1&
b1001000 0
#576000
0!
0&
#580000
1!
1&
b1001001 0
#584000
0!
0&
#588000
1!
1&
b1001010 0
#592000
0!
0&
#596000
1!
1&
b1001011 0
#600000
0!
0&
#604000
1!
1&
b1001100 0
#608000
0!
0&
#612000
1!
1&
b1001101 0
#616000
0!
0&
#620000
1!
1&
b1001110 0
#624000
0!
0&
#628000
1!
1&
b1001111 0
#632000
0!
0&
#636000
1!
1&
b1010000 0
#640000
0!
0&
#644000
1!
1&
b1010001 0
#648000
0!
0&
#652000
1!
1&
b1010010 0
#656000
0!
0&
#660000
1!
1&
b1010011 0
#664000
0!
0&
#668000
1!
1&
b1010100 0
#672000
0!
0&
#676000
1!
1&
b1010101 0
#680000
0!
0&
#684000
1!
1&
b1010110 0
#688000
0!
0&
#692000
1!
1&
b1010111 0
#696000
0!
0&
#700000
1!
1&
b1011000 0
#704000
0!
0&
#708000
1!
1&
b1011001 0
#712000
0!
0&
#716000
1!
1&
b1011010 0
#720000
0!
0&
#724000
1!
1&
b1011011 0
#728000
0!
0&
#732000
1!
1&
b1011100 0
#736000
0!
0&
#740000
1!
1&
b1011101 0
#744000
0!
0&
#748000
1!
1&
b1011110 0
#752000
0!
0&
#756000
1!
1&
b1011111 0
#760000
0!
0&
#764000
1!
1&
b1100000 0
#768000
0!
0&
#772000
1!
1&
b1100001 0
#776000
0!
0&
#780000
1!
1&
b1100010 0
#784000
0!
0&
#788000
1!
1&
b1100011 0
#792000
0!
0&
#796000
1!
1&
b1100100 0
#800000
0!
0&
#804000
1!
1&
b1100101 0
#808000
0!
0&
#812000
1!
1&
b1100110 0
#816000
0!
0&
#820000
1!
1&
b1100111 0
#824000
0!
0&
#828000
1!
1&
b1101000 0
#832000
0!
0&
#836000
1!
1&
b1101001 0
#840000
0!
0&
#844000
1!
1&
b1101010 0
#848000
0!
0&
#852000
1!
1&
b1101011 0
#856000
0!
0&
#860000
1!
1&
b1101100 0
#864000
0!
0&
#868000
1!
1&
b1101101 0
#872000
0!
0&
#876000
1!
1&
b1101110 0
#880000
0!
0&
#884000
1!
1&
b1101111 0
#888000
0!
0&
#892000
1!
1&
b1110000 0
#896000
0!
0&
#900000
1!
1&
b1110001 0
#904000
0!
0&
#908000
1!
1&
b1110010 0
#912000
0!
0&
#916000
1!
1&
b1110011 0
#920000
0!
0&
#924000
1!
1&
b1110100 0
#928000
0!
0&
#932000
1!
1&
b1110101 0
#936000
0!
0&
#940000
1!
1&
b1110110 0
#944000
0!
0&
#948000
1!
1&
b1110111 0
#952000
0!
0&
#956000
1!
1&
b1111000 0
#960000
0!
0&
#964000
1!
1&
b1111001 0
#968000
0!
0&
#972000
1!
1&
b1111010 0
#976000
0!
0&
#980000
1!
1&
b1111011 0
#984000
0!
0&
#988000
1!
1&
b1111100 0
#992000
0!
0&
#996000
1!
1&
b1111101 0
#1000000
0!
1$
0&
1)
